{
    "name": "Doc Greenway",
    "image": "",
    "description": "",
    "sermons": [
        {
            "title": "A Sure Leading",
            "url": "https:\/\/sermonindex.info\/SID27131",
            "size": "0",
            "format": "mp3",
            "scripture": "",
            "topic": "Christian Life",
            "description": "",
            "download": "https:\/\/sermonindex.info\/SID27131-download",
            "preacher_name": "Doc Greenway",
            "preacher_image": "",
            "preacher_description": "",
            "_scripture": []
        },
        {
            "title": "Better Things",
            "url": "https:\/\/sermonindex.info\/SID27104",
            "size": "0",
            "format": "mp3",
            "scripture": "",
            "topic": "New Covenant",
            "description": "",
            "download": "https:\/\/sermonindex.info\/SID27104-download",
            "preacher_name": "Doc Greenway",
            "preacher_image": "",
            "preacher_description": "",
            "_scripture": []
        },
        {
            "title": "Christ in the Home",
            "url": "https:\/\/sermonindex.info\/SID27132",
            "size": "0",
            "format": "mp3",
            "scripture": "",
            "topic": "Home",
            "description": "",
            "download": "https:\/\/sermonindex.info\/SID27132-download",
            "preacher_name": "Doc Greenway",
            "preacher_image": "",
            "preacher_description": "",
            "_scripture": []
        },
        {
            "title": "Deeper Knowledge",
            "url": "https:\/\/sermonindex.info\/SID27105",
            "size": "0",
            "format": "mp3",
            "scripture": "",
            "topic": "Knowledge",
            "description": "",
            "download": "https:\/\/sermonindex.info\/SID27105-download",
            "preacher_name": "Doc Greenway",
            "preacher_image": "",
            "preacher_description": "",
            "_scripture": []
        },
        {
            "title": "Discipleship",
            "url": "https:\/\/sermonindex.info\/SID27106",
            "size": "0",
            "format": "mp3",
            "scripture": "",
            "topic": "Discipleship",
            "description": "",
            "download": "https:\/\/sermonindex.info\/SID27106-download",
            "preacher_name": "Doc Greenway",
            "preacher_image": "",
            "preacher_description": "",
            "_scripture": []
        },
        {
            "title": "Growth in Spiritual Consciousness and Conduct",
            "url": "https:\/\/sermonindex.info\/SID27107",
            "size": "0",
            "format": "mp3",
            "scripture": "",
            "topic": "Spiritual",
            "description": "",
            "download": "https:\/\/sermonindex.info\/SID27107-download",
            "preacher_name": "Doc Greenway",
            "preacher_image": "",
            "preacher_description": "",
            "_scripture": []
        },
        {
            "title": "Growth in Spiritual Constancy",
            "url": "https:\/\/sermonindex.info\/SID27109",
            "size": "0",
            "format": "mp3",
            "scripture": "",
            "topic": "Spiritual Growth",
            "description": "",
            "download": "https:\/\/sermonindex.info\/SID27109-download",
            "preacher_name": "Doc Greenway",
            "preacher_image": "",
            "preacher_description": "",
            "_scripture": []
        },
        {
            "title": "I Will Build My Church",
            "url": "https:\/\/sermonindex.info\/SID27108",
            "size": "0",
            "format": "mp3",
            "scripture": "Matthew 16:18",
            "topic": "Church",
            "description": "",
            "download": "https:\/\/sermonindex.info\/SID27108-download",
            "preacher_name": "Doc Greenway",
            "preacher_image": "",
            "preacher_description": "",
            "_scripture": [
                {
                    "book": "Matthew",
                    "chapter": "16"
                }
            ]
        },
        {
            "title": "Practical Christianity",
            "url": "https:\/\/sermonindex.info\/SID27113",
            "size": "0",
            "format": "mp3",
            "scripture": "",
            "topic": "Practical",
            "description": "",
            "download": "https:\/\/sermonindex.info\/SID27113-download",
            "preacher_name": "Doc Greenway",
            "preacher_image": "",
            "preacher_description": "",
            "_scripture": []
        },
        {
            "title": "Revival - Part 1",
            "url": "https:\/\/sermonindex.info\/SID27117",
            "size": "0",
            "format": "mp3",
            "scripture": "",
            "topic": "Revival",
            "description": "",
            "download": "https:\/\/sermonindex.info\/SID27117-download",
            "preacher_name": "Doc Greenway",
            "preacher_image": "",
            "preacher_description": "",
            "_scripture": []
        },
        {
            "title": "Revival - Part 10",
            "url": "https:\/\/sermonindex.info\/SID27126",
            "size": "0",
            "format": "mp3",
            "scripture": "",
            "topic": "Revival",
            "description": "",
            "download": "https:\/\/sermonindex.info\/SID27126-download",
            "preacher_name": "Doc Greenway",
            "preacher_image": "",
            "preacher_description": "",
            "_scripture": []
        },
        {
            "title": "Revival - Part 11",
            "url": "https:\/\/sermonindex.info\/SID27127",
            "size": "0",
            "format": "mp3",
            "scripture": "",
            "topic": "Revival",
            "description": "",
            "download": "https:\/\/sermonindex.info\/SID27127-download",
            "preacher_name": "Doc Greenway",
            "preacher_image": "",
            "preacher_description": "",
            "_scripture": []
        },
        {
            "title": "Revival - Part 12",
            "url": "https:\/\/sermonindex.info\/SID27128",
            "size": "0",
            "format": "mp3",
            "scripture": "",
            "topic": "Revival",
            "description": "",
            "download": "https:\/\/sermonindex.info\/SID27128-download",
            "preacher_name": "Doc Greenway",
            "preacher_image": "",
            "preacher_description": "",
            "_scripture": []
        },
        {
            "title": "Revival - Part 13",
            "url": "https:\/\/sermonindex.info\/SID27129",
            "size": "0",
            "format": "mp3",
            "scripture": "",
            "topic": "Revival",
            "description": "",
            "download": "https:\/\/sermonindex.info\/SID27129-download",
            "preacher_name": "Doc Greenway",
            "preacher_image": "",
            "preacher_description": "",
            "_scripture": []
        },
        {
            "title": "Revival - Part 14",
            "url": "https:\/\/sermonindex.info\/SID27130",
            "size": "0",
            "format": "mp3",
            "scripture": "",
            "topic": "Revival",
            "description": "",
            "download": "https:\/\/sermonindex.info\/SID27130-download",
            "preacher_name": "Doc Greenway",
            "preacher_image": "",
            "preacher_description": "",
            "_scripture": []
        },
        {
            "title": "Revival - Part 2",
            "url": "https:\/\/sermonindex.info\/SID27118",
            "size": "0",
            "format": "mp3",
            "scripture": "",
            "topic": "Revival",
            "description": "",
            "download": "https:\/\/sermonindex.info\/SID27118-download",
            "preacher_name": "Doc Greenway",
            "preacher_image": "",
            "preacher_description": "",
            "_scripture": []
        },
        {
            "title": "Revival - Part 3",
            "url": "https:\/\/sermonindex.info\/SID27119",
            "size": "0",
            "format": "mp3",
            "scripture": "",
            "topic": "Revival",
            "description": "",
            "download": "https:\/\/sermonindex.info\/SID27119-download",
            "preacher_name": "Doc Greenway",
            "preacher_image": "",
            "preacher_description": "",
            "_scripture": []
        },
        {
            "title": "Revival - Part 4",
            "url": "https:\/\/sermonindex.info\/SID27120",
            "size": "0",
            "format": "mp3",
            "scripture": "",
            "topic": "Revival",
            "description": "",
            "download": "https:\/\/sermonindex.info\/SID27120-download",
            "preacher_name": "Doc Greenway",
            "preacher_image": "",
            "preacher_description": "",
            "_scripture": []
        },
        {
            "title": "Revival - Part 5",
            "url": "https:\/\/sermonindex.info\/SID27121",
            "size": "0",
            "format": "mp3",
            "scripture": "",
            "topic": "Revival",
            "description": "",
            "download": "https:\/\/sermonindex.info\/SID27121-download",
            "preacher_name": "Doc Greenway",
            "preacher_image": "",
            "preacher_description": "",
            "_scripture": []
        },
        {
            "title": "Revival - Part 6",
            "url": "https:\/\/sermonindex.info\/SID27122",
            "size": "0",
            "format": "mp3",
            "scripture": "",
            "topic": "Revival",
            "description": "",
            "download": "https:\/\/sermonindex.info\/SID27122-download",
            "preacher_name": "Doc Greenway",
            "preacher_image": "",
            "preacher_description": "",
            "_scripture": []
        },
        {
            "title": "Revival - Part 7",
            "url": "https:\/\/sermonindex.info\/SID27123",
            "size": "0",
            "format": "mp3",
            "scripture": "",
            "topic": "Revival",
            "description": "",
            "download": "https:\/\/sermonindex.info\/SID27123-download",
            "preacher_name": "Doc Greenway",
            "preacher_image": "",
            "preacher_description": "",
            "_scripture": []
        },
        {
            "title": "Revival - Part 8",
            "url": "https:\/\/sermonindex.info\/SID27124",
            "size": "0",
            "format": "mp3",
            "scripture": "",
            "topic": "Revival",
            "description": "",
            "download": "https:\/\/sermonindex.info\/SID27124-download",
            "preacher_name": "Doc Greenway",
            "preacher_image": "",
            "preacher_description": "",
            "_scripture": []
        },
        {
            "title": "Revival - Part 9",
            "url": "https:\/\/sermonindex.info\/SID27125",
            "size": "0",
            "format": "mp3",
            "scripture": "",
            "topic": "Revival",
            "description": "",
            "download": "https:\/\/sermonindex.info\/SID27125-download",
            "preacher_name": "Doc Greenway",
            "preacher_image": "",
            "preacher_description": "",
            "_scripture": []
        },
        {
            "title": "Revival in our Day",
            "url": "https:\/\/sermonindex.info\/SID27112",
            "size": "0",
            "format": "mp3",
            "scripture": "",
            "topic": "Revival",
            "description": "",
            "download": "https:\/\/sermonindex.info\/SID27112-download",
            "preacher_name": "Doc Greenway",
            "preacher_image": "",
            "preacher_description": "",
            "_scripture": []
        },
        {
            "title": "Romans 12:1-2",
            "url": "https:\/\/sermonindex.info\/SID27133",
            "size": "0",
            "format": "mp3",
            "scripture": "Romans 12:1-2",
            "topic": "Romans",
            "description": "",
            "download": "https:\/\/sermonindex.info\/SID27133-download",
            "preacher_name": "Doc Greenway",
            "preacher_image": "",
            "preacher_description": "",
            "_scripture": [
                {
                    "book": "Romans",
                    "chapter": "12"
                }
            ]
        },
        {
            "title": "Romans 12:12",
            "url": "https:\/\/sermonindex.info\/SID27138",
            "size": "0",
            "format": "mp3",
            "scripture": "Romans 12:12",
            "topic": "Romans",
            "description": "",
            "download": "https:\/\/sermonindex.info\/SID27138-download",
            "preacher_name": "Doc Greenway",
            "preacher_image": "",
            "preacher_description": "",
            "_scripture": [
                {
                    "book": "Romans",
                    "chapter": "12"
                }
            ]
        },
        {
            "title": "Romans 12:14-17",
            "url": "https:\/\/sermonindex.info\/SID27136",
            "size": "0",
            "format": "mp3",
            "scripture": "Romans 12:14-17",
            "topic": "Romans",
            "description": "",
            "download": "https:\/\/sermonindex.info\/SID27136-download",
            "preacher_name": "Doc Greenway",
            "preacher_image": "",
            "preacher_description": "",
            "_scripture": [
                {
                    "book": "Romans",
                    "chapter": "12"
                }
            ]
        },
        {
            "title": "Romans 12:18",
            "url": "https:\/\/sermonindex.info\/SID27137",
            "size": "0",
            "format": "mp3",
            "scripture": "Romans 12:18",
            "topic": "Romans",
            "description": "",
            "download": "https:\/\/sermonindex.info\/SID27137-download",
            "preacher_name": "Doc Greenway",
            "preacher_image": "",
            "preacher_description": "",
            "_scripture": [
                {
                    "book": "Romans",
                    "chapter": "12"
                }
            ]
        },
        {
            "title": "Romans 12:6-8",
            "url": "https:\/\/sermonindex.info\/SID27134",
            "size": "0",
            "format": "mp3",
            "scripture": "Romans 12:6-8",
            "topic": "Romans",
            "description": "",
            "download": "https:\/\/sermonindex.info\/SID27134-download",
            "preacher_name": "Doc Greenway",
            "preacher_image": "",
            "preacher_description": "",
            "_scripture": [
                {
                    "book": "Romans",
                    "chapter": "12"
                }
            ]
        },
        {
            "title": "Romans 12:9-11",
            "url": "https:\/\/sermonindex.info\/SID27135",
            "size": "0",
            "format": "mp3",
            "scripture": "Romans 12:9-11",
            "topic": "Romans",
            "description": "",
            "download": "https:\/\/sermonindex.info\/SID27135-download",
            "preacher_name": "Doc Greenway",
            "preacher_image": "",
            "preacher_description": "",
            "_scripture": [
                {
                    "book": "Romans",
                    "chapter": "12"
                }
            ]
        },
        {
            "title": "The Folly and Glory of the Cross",
            "url": "https:\/\/sermonindex.info\/SID27111",
            "size": "0",
            "format": "mp3",
            "scripture": "",
            "topic": "Cross",
            "description": "",
            "download": "https:\/\/sermonindex.info\/SID27111-download",
            "preacher_name": "Doc Greenway",
            "preacher_image": "",
            "preacher_description": "",
            "_scripture": []
        },
        {
            "title": "The New Covenant in Communion",
            "url": "https:\/\/sermonindex.info\/SID27110",
            "size": "0",
            "format": "mp3",
            "scripture": "",
            "topic": "Communion",
            "description": "",
            "download": "https:\/\/sermonindex.info\/SID27110-download",
            "preacher_name": "Doc Greenway",
            "preacher_image": "",
            "preacher_description": "",
            "_scripture": []
        },
        {
            "title": "Thraldom",
            "url": "https:\/\/sermonindex.info\/SID27139",
            "size": "0",
            "format": "mp3",
            "scripture": "",
            "topic": "Bondage",
            "description": "",
            "download": "https:\/\/sermonindex.info\/SID27139-download",
            "preacher_name": "Doc Greenway",
            "preacher_image": "",
            "preacher_description": "",
            "_scripture": []
        },
        {
            "title": "Unity",
            "url": "https:\/\/sermonindex.info\/SID27114",
            "size": "0",
            "format": "mp3",
            "scripture": "",
            "topic": "Unity",
            "description": "",
            "download": "https:\/\/sermonindex.info\/SID27114-download",
            "preacher_name": "Doc Greenway",
            "preacher_image": "",
            "preacher_description": "",
            "_scripture": []
        },
        {
            "title": "Victory in Adversity",
            "url": "https:\/\/sermonindex.info\/SID27140",
            "size": "0",
            "format": "mp3",
            "scripture": "",
            "topic": "Adversity",
            "description": "",
            "download": "https:\/\/sermonindex.info\/SID27140-download",
            "preacher_name": "Doc Greenway",
            "preacher_image": "",
            "preacher_description": "",
            "_scripture": []
        },
        {
            "title": "Walking With God - Enoch",
            "url": "https:\/\/sermonindex.info\/SID27116",
            "size": "0",
            "format": "mp3",
            "scripture": "",
            "topic": "Enoch",
            "description": "",
            "download": "https:\/\/sermonindex.info\/SID27116-download",
            "preacher_name": "Doc Greenway",
            "preacher_image": "",
            "preacher_description": "",
            "_scripture": []
        },
        {
            "title": "When Jesus Draws Near",
            "url": "https:\/\/sermonindex.info\/SID27115",
            "size": "0",
            "format": "mp3",
            "scripture": "",
            "topic": "Jesus",
            "description": "",
            "download": "https:\/\/sermonindex.info\/SID27115-download",
            "preacher_name": "Doc Greenway",
            "preacher_image": "",
            "preacher_description": "",
            "_scripture": []
        }
    ]
}