{
    "name": "Person Of Christ",
    "description": "",
    "sermons": [
        {
            "title": "The Person of Christ",
            "url": "http:\/\/api.sermonindex.net\/SID23680",
            "size": "0",
            "format": "mp3",
            "scripture": "",
            "topic": "Person Of Christ",
            "description": "",
            "download": "http:\/\/api.sermonindex.net\/SID23680-download",
            "speaker_name": "David Gooding",
            "_scripture": []
        }
    ]
}